latextools/__init__.py
latextools/command.py
latextools/common_format.py
latextools/common_preamble.py
latextools/content.py
latextools/convert.py
latextools/document.py
latextools/file.py
latextools/package.py
latextools/pdf.py
latextools/project.py
latextools/shortcuts.py
latextools/str_util.py
latextools/plot/__init__.py
latextools/plot/artist_wrap.py
latextools/plot/bar_plot.py
latextools/plot/scatter_plot.py
latextools-0.5.0.dist-info/LICENSE.txt
latextools-0.5.0.dist-info/METADATA
latextools-0.5.0.dist-info/WHEEL
latextools-0.5.0.dist-info/top_level.txt
latextools-0.5.0.dist-info/RECORD
