Metadata-Version: 2.1
Name: latextools
Version: 0.5.0
Summary: A collection of tools for building, rendering, and converting Latex documents
Home-page: https://github.com/cduck/latextools
Download-URL: https://github.com/cduck/latextools/archive/0.5.0.tar.gz
Author: Casey Duckering
License: UNKNOWN
Keywords: LaTeX
Platform: UNKNOWN
Classifier: License :: OSI Approved :: MIT License
Classifier: Development Status :: 3 - Alpha
Classifier: Programming Language :: Python :: 3
Classifier: Framework :: IPython
Classifier: Framework :: Jupyter
License-File: LICENSE.txt
Requires-Dist: fs
Provides-Extra: all
Requires-Dist: drawsvg[raster] (~=2.0) ; extra == 'all'
Provides-Extra: dev
Requires-Dist: twine ; extra == 'dev'
Provides-Extra: svg
Requires-Dist: drawsvg[raster] (~=2.0) ; extra == 'svg'
